crmonitor/__init__.py
crmonitor/common/__init__.py
crmonitor/common/cache.py
crmonitor/common/config.py
crmonitor/common/helper.py
crmonitor/common/road_network.py
crmonitor/common/scenario_type.py
crmonitor/common/vehicle.py
crmonitor/common/world.py
crmonitor/config.yaml
crmonitor/errors.py
crmonitor/evaluation/__init__.py
crmonitor/evaluation/evaluation.py
crmonitor/evaluation/predicate_interface.py
crmonitor/evaluation/proposition_evaluation.py
crmonitor/evaluation/visitors/__init__.py
crmonitor/evaluation/visitors/_base.py
crmonitor/evaluation/visitors/offline_evaluation_visitor.py
crmonitor/evaluation/visitors/online_evaluation_visitor.py
crmonitor/monitor/__init__.py
crmonitor/monitor/monitor_creation_visitor.py
crmonitor/monitor/monitor_node.py
crmonitor/monitor/proposition_robustness.py
crmonitor/monitor/rtamt_monitor_stl.py
crmonitor/monitor/specification_dict.py
crmonitor/monitor/visitors.py
crmonitor/mpr/__init__.py
crmonitor/mpr/learning/__init__.py
crmonitor/mpr/learning/_split_data.py
crmonitor/mpr/learning/data_generation.py
crmonitor/mpr/learning/data_loader.py
crmonitor/mpr/learning/error.py
crmonitor/mpr/learning/exact_gp_model.py
crmonitor/mpr/learning/feature_extractor.py
crmonitor/mpr/learning/feature_variables.py
crmonitor/mpr/learning/model_evaluator.py
crmonitor/mpr/learning/model_trainer.py
crmonitor/mpr/models/intersection/.gitkeep
crmonitor/mpr/models/interstate/brakes_abruptly.p
crmonitor/mpr/models/interstate/brakes_abruptly_relative.p
crmonitor/mpr/models/interstate/close_to_left_bound.p
crmonitor/mpr/models/interstate/close_to_right_bound.p
crmonitor/mpr/models/interstate/cut_in.p
crmonitor/mpr/models/interstate/drives_faster.p
crmonitor/mpr/models/interstate/drives_leftmost.p
crmonitor/mpr/models/interstate/drives_rightmost.p
crmonitor/mpr/models/interstate/drives_with_slightly_higher_speed.p
crmonitor/mpr/models/interstate/exist_standing_leading_vehicle.p
crmonitor/mpr/models/interstate/has_congestion_velocity.p
commonroad_stl_monitor-2025.1.1.dist-info/METADATA
commonroad_stl_monitor-2025.1.1.dist-info/WHEEL
commonroad_stl_monitor-2025.1.1.dist-info/licenses/LICENSE.txt
commonroad_stl_monitor-2025.1.1.dist-info/RECORD
